Metadata-Version: 1.1
Name: bfabio.pymodbus
Version: 1.3.0.1
Summary: A fully featured modbus protocol stack in python
Home-page: https://github.com/riptideio/pymodbus/
Author: dhoomakethu
Author-email: otlasanju@gmail.com
License: BSD
Keywords: modbus,twisted,scada
Platform: Linux
Platform: Mac OS X
Platform: Win
Classifier: Development Status :: 4 - Beta
Classifier: Environment :: Console
Classifier: Environment :: X11 Applications :: GTK
Classifier: Framework :: Twisted
Classifier: Intended Audience :: Developers
Classifier: License :: OSI Approved :: BSD License
Classifier: Operating System :: POSIX :: Linux
Classifier: Operating System :: Unix
Classifier: Programming Language :: Python
Classifier: Topic :: System :: Networking
Classifier: Topic :: Utilities
